[
    {
        "node_id": "1",
        "max_sparsity": 0.5,
        "min_rtt": 8,
        "max_rtt": 10,
        "min_pl": 0.01,
        "rtt_factor": 0.5,
        "pl_factor": 0,
        "sparsity_factor": 1,
        "encoding_strategy": "adaptive"
    },
    {
        "node_id": "2",
        "max_sparsity": 0.5,
        "min_rtt": 8,
        "max_rtt": 10,
        "min_pl": 0.01,
        "rtt_factor": 0.5,
        "pl_factor": 0,
        "sparsity_factor": 1,
        "encoding_strategy": "adaptive"
    }
]